pygpc/AbstractModel.py
pygpc/Algorithm.py
pygpc/Basis.py
pygpc/BasisFunction.py
pygpc/Classifier.py
pygpc/Computation.py
pygpc/GPC.py
pygpc/Gradient.py
pygpc/Grid.py
pygpc/MEGPC.py
pygpc/Problem.py
pygpc/Quadrature.py
pygpc/RandomParameter.py
pygpc/SGPC.py
pygpc/Session.py
pygpc/Test.py
pygpc/TestBench.py
pygpc/ValidationSet.py
pygpc/Visualization.py
pygpc/Worker.py
pygpc/__init__.py
pygpc/io.py
pygpc/misc.py
pygpc/oakley_ohagan_2004_M.txt
pygpc/oakley_ohagan_2004_a1.txt
pygpc/oakley_ohagan_2004_a2.txt
pygpc/oakley_ohagan_2004_a3.txt
pygpc/postprocessing.py
pygpc/pygpc_extensions.cp310-win_amd64.pyd
pygpc/sobol_saltelli.py
pygpc/sobol_saltelli_directions.hdf5
pygpc/test_utils.py
pygpc/validation.py
pygpc/testfunctions/__init__.py
pygpc/testfunctions/euber_libV3.py
pygpc/testfunctions/testfunctions.py
pygpc-0.4.4.dist-info/licenses/LICENSE
pygpc-0.4.4.dist-info/METADATA
pygpc-0.4.4.dist-info/WHEEL
pygpc-0.4.4.dist-info/top_level.txt
pygpc-0.4.4.dist-info/RECORD
